LICENSE
MANIFEST.in
NOTICE
README.rst
setup.py
./PyJobRunner.egg-info/PKG-INFO
./PyJobRunner.egg-info/SOURCES.txt
./PyJobRunner.egg-info/dependency_links.txt
./PyJobRunner.egg-info/requires.txt
./PyJobRunner.egg-info/top_level.txt
./jobrunner/__init__.py
./jobrunner/__meta__.py
./jobrunner/options.py
./jobrunner/api/__init__.py
./jobrunner/api/_commands.py
./jobrunner/cli/__init__.py
./jobrunner/cli/_commands.py
./jobrunner/cli/_jobrunner.py
./jobrunner/instruments/__init__.py
./jobrunner/instruments/flashx.py
./jobrunner/lib/__init__.py
./jobrunner/lib/_archivetools.py
./jobrunner/lib/_colors.py
./jobrunner/lib/_console.py
./jobrunner/lib/_filetools.py
./jobrunner/lib/_parsetools.py
./jobrunner/lib/_utilities.py
bin/cmd.py
jobrunner/scripts/catlog
jobrunner/scripts/catloglast
jobrunner/scripts/jobrunner
jobrunner/scripts/logdiff
media/icon.svg
requirements/core.txt
requirements/instruments.txt