Metadata-Version: 2.1
Name: PyJobRunner
Version: 2023.11.6
Summary: Job runner for scientific computing workloads
Author: Akash Dhruv
License: Apache Software License
Classifier: Programming Language :: Python :: 3.8
Classifier: License :: OSI Approved :: Apache Software License
License-File: LICENSE
License-File: NOTICE
Requires-Dist: click
Requires-Dist: toml
Requires-Dist: pyyaml
Requires-Dist: alive-progress==3.1.4
